MANIFEST.in
README.md
setup.cfg
setup.py
roadmap/__init__.py
roadmap/resources/__init__.py
roadmap/resources/app_users.py
roadmap/resources/feedback.py
roadmap/resources/ideas.py
roadmap/resources/items.py
roadmap/resources/model.py
roadmap/resources/roadmaps.py
roadmap/resources/stories.py
roadmap/resources/subscribers.py
roadmap_py.egg-info/PKG-INFO
roadmap_py.egg-info/SOURCES.txt
roadmap_py.egg-info/dependency_links.txt
roadmap_py.egg-info/requires.txt
roadmap_py.egg-info/top_level.txt